integration_wetsuits/__init__.py
integration_wetsuits/edi.py
integration_wetsuits/edi_dict.py
integration_wetsuits/itsp.py
integration_wetsuits-1.0.1.dist-info/METADATA
integration_wetsuits-1.0.1.dist-info/WHEEL
integration_wetsuits-1.0.1.dist-info/top_level.txt
integration_wetsuits-1.0.1.dist-info/RECORD
