Metadata-Version: 2.1
Name: integration-wetsuits
Version: 1.0.1
Summary: integration
Author-email: Name <info@wetsuits.com>
Classifier: Development Status :: 4 - Beta
Classifier: License :: OSI Approved :: MIT License
Classifier: Programming Language :: Python :: 3
Classifier: Operating System :: OS Independent
Requires-Python: >=3.10
Requires-Dist: requests ==2.31.0
Requires-Dist: pandas ==2.0.3
Requires-Dist: validx ==0.8.1
